sdkgen/__init__.py
sdkgen/cli.py
sdkgen/analyzers/__init__.py
sdkgen/analyzers/endpoint_analyzer.py
sdkgen/analyzers/namespace_analyzer.py
sdkgen/analyzers/naming_analyzer.py
sdkgen/analyzers/nested_detector.py
sdkgen/core/__init__.py
sdkgen/core/ir.py
sdkgen/core/ir_builder.py
sdkgen/core/parser.py
sdkgen/core/resolver.py
sdkgen/core/schema_analyzer.py
sdkgen/core/type_mapper.py
sdkgen/generators/__init__.py
sdkgen/generators/python/__init__.py
sdkgen/generators/python/client_gen.py
sdkgen/generators/python/converters_gen.py
sdkgen/generators/python/enums_gen.py
sdkgen/generators/python/generator.py
sdkgen/generators/python/models_gen.py
sdkgen/generators/python/namespace_gen.py
sdkgen/generators/python/resources_gen.py
sdkgen/generators/python/utils_gen.py
sdkgen/utils/__init__.py
sdkgen/utils/case_converter.py
sdkgen/utils/http_cache.py
sdkgen/utils/name_sanitizer.py
sdkgen-0.2.0.dist-info/METADATA
sdkgen-0.2.0.dist-info/WHEEL
sdkgen-0.2.0.dist-info/entry_points.txt
sdkgen-0.2.0.dist-info/RECORD
