Metadata-Version: 2.4
Name: sdkgen
Version: 0.2.0
Summary: Multi-language SDK generator from OpenAPI specifications
Project-URL: Homepage, https://github.com/4thel00z/sdkgen
Project-URL: Repository, https://github.com/4thel00z/sdkgen
Project-URL: Documentation, https://github.com/4thel00z/sdkgen/blob/master/docs
Project-URL: Issues, https://github.com/4thel00z/sdkgen/issues
Author-email: Mohamed Tahrioui <mohamed.tahrioui@example.com>
License: MIT
Keywords: api,async,code-generation,generator,openapi,sdk,type-safe
Classifier: Development Status :: 4 - Beta
Classifier: Framework :: AsyncIO
Classifier: Intended Audience :: Developers
Classifier: License :: OSI Approved :: MIT License
Classifier: Programming Language :: Python :: 3.12
Classifier: Programming Language :: Python :: 3.13
Classifier: Topic :: Software Development :: Code Generators
Classifier: Topic :: Software Development :: Libraries
Classifier: Typing :: Typed
Requires-Python: >=3.12
Requires-Dist: click>=8.1.0
Requires-Dist: httpx>=0.27.0
Requires-Dist: jinja2>=3.1.0
Requires-Dist: jsonref>=1.1.0
Requires-Dist: pydantic>=2.0
Requires-Dist: pyyaml>=6.0
Provides-Extra: dev
Requires-Dist: mypy>=1.13.0; extra == 'dev'
Requires-Dist: pytest-asyncio>=0.23.0; extra == 'dev'
Requires-Dist: pytest-cov>=6.0.0; extra == 'dev'
Requires-Dist: pytest>=8.0.0; extra == 'dev'
Requires-Dist: ruff>=0.7.0; extra == 'dev'
Requires-Dist: twine>=5.0.0; extra == 'dev'
Requires-Dist: types-pyyaml>=6.0; extra == 'dev'
